{"name":"Lanci","version":"1.1","download_url":"https:\/\/github.com\/divea-server\/lanci\/archive\/master.zip","sections":{"description":"\nO plugin Lanc\u00ed \u00e9 um apanhado de diversas funcionalidades para otimizar seu Wordpress nos servidores da D\u00edvea.\n<br><br>\n<h3>Gest\u00e3o autom\u00e1tica de Cache<\/h3>\nEle faz a gest\u00e3o dos caches Regis e do Proxy do Nginx de forma autom\u00e1tica, limpando-os automaticamente ao alterar, criar ou deletar um post ou fazer qualquer outro tipo de altera\u00e7\u00e3o.\n<ul>\n\t<li>Redis 2.0.15<\/li>\n  \t<li>Nginx Cache 1.0.5<\/li>\n<\/ul>\n<h3>Inser\u00e7\u00e3o de tags<\/h3>\nUm lugar s\u00f3 para administrar as principais tags de acompanhamento no dia a dia. Facebook Pixel, Google Analyitcs, Google Tag Manager e ainda um campo para colocar outras tags que precisar."}}